AUTHORS.md
CHANGELOG.md
LICENSE
MANIFEST.in
README.rst
pyproject.toml
setup.py
tox.ini
docs/Makefile
docs/README.md
docs/conf.py
docs/index.rst
docs/_static/.gitkeep
docs/_static/pyseobnr_120px.png
docs/_static/pyseobnr_64px.png
docs/source/basic_usage.rst
docs/source/citations.rst
docs/source/expert_mode.rst
docs/source/how_to_contribute.rst
docs/source/installation.rst
docs/source/notebooks/example_SEOBNRv5EHM.md
docs/source/notebooks/example_precession.md
docs/source/notebooks/getting_started.md
docs/source/notebooks/pseob_example.md
docs/source/notebooks/pycbc_example.md
docs/templates/custom-class-template.rst
docs/templates/custom-module-template.rst
pyseobnr/__init__.py
pyseobnr/_version.py
pyseobnr/generate_waveform.py
pyseobnr.egg-info/PKG-INFO
pyseobnr.egg-info/SOURCES.txt
pyseobnr.egg-info/dependency_links.txt
pyseobnr.egg-info/entry_points.txt
pyseobnr.egg-info/not-zip-safe
pyseobnr.egg-info/requires.txt
pyseobnr.egg-info/top_level.txt
pyseobnr/auxiliary/__init__.py
pyseobnr/auxiliary/external_models/__init__.py
pyseobnr/auxiliary/external_models/default_settings.py
pyseobnr/auxiliary/external_models/external_models.py
pyseobnr/auxiliary/interpolate/__init__.py
pyseobnr/auxiliary/interpolate/vector_spline.py
pyseobnr/auxiliary/mode_mixing/__init__.py
pyseobnr/auxiliary/mode_mixing/auxiliary_functions_modemixing.py
pyseobnr/auxiliary/sanity_checks/EOB_matches.py
pyseobnr/auxiliary/sanity_checks/NRSur_IV_difference.py
pyseobnr/auxiliary/sanity_checks/NRSur_matches.py
pyseobnr/auxiliary/sanity_checks/NR_mismatches.py
pyseobnr/auxiliary/sanity_checks/aligned_matches_v5PHM.py
pyseobnr/auxiliary/sanity_checks/aligned_matches_v5PHM.sh
pyseobnr/auxiliary/sanity_checks/aligned_matches_v5PHM_commentedMatch.py
pyseobnr/auxiliary/sanity_checks/aligned_matches_v5PHM_commentedMatch.sh
pyseobnr/auxiliary/sanity_checks/amp_hierarchy_test_prec_submission.py
pyseobnr/auxiliary/sanity_checks/amplitude_hierarchy_test.py
pyseobnr/auxiliary/sanity_checks/amplitude_hierarchy_test_precessing.py
pyseobnr/auxiliary/sanity_checks/attachment_smoothness_test.py
pyseobnr/auxiliary/sanity_checks/battery_of_tests.py
pyseobnr/auxiliary/sanity_checks/mismatch_PA_polarization_precession.py
