Metadata-Version: 2.4
Name: pyseobnr
Version: 0.3.5
Summary: Gravitational wave modelling within the effective-one-body framework
Author-email: Serguei Ossokine <serguei.ossokine@tutanota.com>, Lorenzo Pompili <lorenzo.pompili@ligo.org>, Deyan Mihaylov <deyan.mihaylov@ligo.org>, Antoni Ramos Buades <antoni.ramos-buades@ligo.org>, Michael Puerrer <michael.puerrer@ligo.org>, Hector Estelles <hector.estelles@ligo.org>
Maintainer-email: Raffi Enficiaud <raffi.enficiaud@ligo.org>, Lorenzo Pompili <lorenzo.pompili@ligo.org>, Hector Estelles <hector.estelles@ligo.org>
License-Expression: GPL-3.0-or-later
Project-URL: homepage, https://git.ligo.org/waveforms/software/pyseobnr
Project-URL: documentation, https://waveforms.docs.ligo.org/software/pyseobnr/
Project-URL: issues, https://git.ligo.org/waveforms/software/pyseobnr/-/issues
Project-URL: changelog, https://git.ligo.org/waveforms/software/pyseobnr/-/blob/main/CHANGELOG.md
Classifier: Development Status :: 5 - Production/Stable
Classifier: Intended Audience :: Education
Classifier: Intended Audience :: Science/Research
Classifier: Operating System :: MacOS
Classifier: Operating System :: Unix
Classifier: Programming Language :: Python :: 3
Classifier: Topic :: Scientific/Engineering :: Mathematics
Classifier: Topic :: Scientific/Engineering :: Physics
Requires-Python: >=3.8
License-File: LICENSE
License-File: AUTHORS.md
Requires-Dist: numpy>=1.23.0
Requires-Dist: scipy>=1.8.0
Requires-Dist: h5py
Requires-Dist: numexpr
Requires-Dist: numba
Requires-Dist: qnm
Requires-Dist: scri
Requires-Dist: pygsl_lite
Requires-Dist: lalsuite
Requires-Dist: importlib_resources; python_version < "3.10"
Provides-Extra: checks
Requires-Dist: bilby; extra == "checks"
Requires-Dist: gwsurrogate; extra == "checks"
Requires-Dist: pathos; extra == "checks"
Requires-Dist: scikit-optimize; extra == "checks"
Requires-Dist: matplotlib; extra == "checks"
Provides-Extra: docs
Requires-Dist: nbsphinx; extra == "docs"
Requires-Dist: numpydoc; extra == "docs"
Requires-Dist: sphinx; extra == "docs"
Requires-Dist: sphinx_rtd_theme; extra == "docs"
Requires-Dist: sphinx-tabs; extra == "docs"
Requires-Dist: cython; extra == "docs"
Requires-Dist: sphinx_gallery; extra == "docs"
Requires-Dist: jupytext; extra == "docs"
Requires-Dist: jupyterlab; extra == "docs"
Requires-Dist: pandas; extra == "docs"
Requires-Dist: pyarrow; extra == "docs"
Requires-Dist: seaborn; extra == "docs"
Requires-Dist: pycbc; extra == "docs"
Requires-Dist: astropy; extra == "docs"
Requires-Dist: gwpy; extra == "docs"
Requires-Dist: matplotlib; extra == "docs"
Provides-Extra: tests
Requires-Dist: pytest; extra == "tests"
Requires-Dist: pytest-sugar; extra == "tests"
Requires-Dist: pandas; extra == "tests"
Requires-Dist: pyarrow; extra == "tests"
Requires-Dist: pycbc; extra == "tests"
Dynamic: license-file
